pymaidol/AnnotationType.py
pymaidol/Errors.py
pymaidol/Executor.py
pymaidol/Nodes.py
pymaidol/Parser.py
pymaidol/Positions.py
pymaidol/SyntaxChecker.py
pymaidol/TemplateBase.py
pymaidol/TemplateRenderer.py
pymaidol/Traversers.py
pymaidol/__init__.py
pymaidol/__main__.py
pymaidol/keywords.py
pymaidol/code_templates/SubClassTemplate.py
pymaidol/code_templates/SubClassTemplate.pymd
pymaidol/code_templates/__init__.py
pymaidol-0.1.3.dist-info/LICENSE
pymaidol-0.1.3.dist-info/METADATA
pymaidol-0.1.3.dist-info/WHEEL
pymaidol-0.1.3.dist-info/top_level.txt
pymaidol-0.1.3.dist-info/RECORD
