Metadata-Version: 2.1
Name: pymaidol
Version: 0.1.3
Summary: A markup gramma that embed python code into text
Author: Eterance
Keywords: Prompt,Markup Language,NLP,AI,GPT
Classifier: Programming Language :: Python :: 3
Classifier: License :: OSI Approved :: MIT License
Classifier: Operating System :: OS Independent
Requires-Python: >=3.10
License-File: LICENSE
Requires-Dist: PythonDelegate (>=0.1.0)
